dbldatagen/__init__.py
dbldatagen/_version.py
dbldatagen/column_generation_spec.py
dbldatagen/column_spec_options.py
dbldatagen/data_analyzer.py
dbldatagen/data_generator.py
dbldatagen/datagen_constants.py
dbldatagen/datarange.py
dbldatagen/datasets_object.py
dbldatagen/daterange.py
dbldatagen/function_builder.py
dbldatagen/html_utils.py
dbldatagen/nrange.py
dbldatagen/schema_parser.py
dbldatagen/spark_singleton.py
dbldatagen/text_generator_plugins.py
dbldatagen/text_generators.py
dbldatagen/utils.py
dbldatagen/constraints/__init__.py
dbldatagen/constraints/chained_relation.py
dbldatagen/constraints/constraint.py
dbldatagen/constraints/literal_range_constraint.py
dbldatagen/constraints/literal_relation_constraint.py
dbldatagen/constraints/negative_values.py
dbldatagen/constraints/positive_values.py
dbldatagen/constraints/ranged_values_constraint.py
dbldatagen/constraints/sql_expr.py
dbldatagen/constraints/unique_combinations.py
dbldatagen/datasets/__init__.py
dbldatagen/datasets/basic_geometries.py
dbldatagen/datasets/basic_process_historian.py
dbldatagen/datasets/basic_telematics.py
dbldatagen/datasets/basic_user.py
dbldatagen/datasets/benchmark_groupby.py
dbldatagen/datasets/dataset_provider.py
dbldatagen/datasets/multi_table_telephony_provider.py
dbldatagen/distributions/__init__.py
dbldatagen/distributions/beta.py
dbldatagen/distributions/data_distribution.py
dbldatagen/distributions/exponential_distribution.py
dbldatagen/distributions/gamma.py
dbldatagen/distributions/normal_distribution.py
dbldatagen-0.4.0.post1.dist-info/LICENSE
dbldatagen-0.4.0.post1.dist-info/METADATA
dbldatagen-0.4.0.post1.dist-info/WHEEL
dbldatagen-0.4.0.post1.dist-info/top_level.txt
dbldatagen-0.4.0.post1.dist-info/RECORD
