Metadata-Version: 2.1
Name: dbldatagen
Version: 0.4.0.post1
Summary: Databricks Labs -  PySpark Synthetic Data Generator
Home-page: https://github.com/databrickslabs/data-generator
Author: Ronan Stokes, Databricks
License: Databricks License
Project-URL: Databricks Labs, https://www.databricks.com/learn/labs
Project-URL: Documentation, https://databrickslabs.github.io/dbldatagen/public_docs/index.html
Classifier: Programming Language :: Python :: 3
Classifier: Operating System :: OS Independent
Classifier: Topic :: Software Development :: Testing
Classifier: Intended Audience :: Developers
Classifier: Intended Audience :: System Administrators
Requires-Python: >=3.8.10
License-File: LICENSE
